COPYING
MANIFEST.in
README.rst
requirements.stable.txt
requirements.txt
setup.py
tasks.py
lino_voga/__init__.py
lino_voga/setup_info.py
lino_voga.egg-info/PKG-INFO
lino_voga.egg-info/SOURCES.txt
lino_voga.egg-info/dependency_links.txt
lino_voga.egg-info/requires.txt
lino_voga.egg-info/top_level.txt
lino_voga/lib/__init__.py
lino_voga/lib/cal/__init__.py
lino_voga/lib/cal/models.py
lino_voga/lib/cal/config/cal/Event/page.pub.html
lino_voga/lib/cal/fixtures/__init__.py
lino_voga/lib/cal/fixtures/demo2.py
lino_voga/lib/cal/fixtures/std.py
lino_voga/lib/contacts/__init__.py
lino_voga/lib/contacts/models.py
lino_voga/lib/contacts/fixtures/__init__.py
lino_voga/lib/contacts/fixtures/demo.py
lino_voga/lib/contacts/fixtures/std.py
lino_voga/lib/contacts/management/__init__.py
lino_voga/lib/contacts/management/commands/__init__.py
lino_voga/lib/contacts/management/commands/garble_persons.py
lino_voga/lib/courses/__init__.py
lino_voga/lib/courses/models.py
lino_voga/lib/courses/ui.py
lino_voga/lib/courses/config/courses/detail.line.html
lino_voga/lib/courses/config/courses/listitem.line.html
lino_voga/lib/courses/fixtures/__init__.py
lino_voga/lib/courses/fixtures/demo.py
lino_voga/lib/invoicing/__init__.py
lino_voga/lib/invoicing/models.py
lino_voga/lib/invoicing/fixtures/__init__.py
lino_voga/lib/invoicing/fixtures/demo_bookings.py
lino_voga/lib/products/__init__.py
lino_voga/lib/products/models.py
lino_voga/lib/roger/__init__.py
lino_voga/lib/roger/courses/__init__.py
lino_voga/lib/roger/courses/models.py
lino_voga/lib/roger/courses/ui.py
lino_voga/lib/roger/courses/fixtures/__init__.py
lino_voga/lib/roger/courses/fixtures/demo.py
lino_voga/lib/roger/courses/fixtures/minimal_ledger.py
lino_voga/lib/roger/courses/fixtures/std.py
lino_voga/lib/roger/courses/management/__init__.py
lino_voga/lib/roger/courses/management/commands/__init__.py
lino_voga/lib/roger/courses/management/commands/eiche2lino.py
lino_voga/lib/rooms/__init__.py
lino_voga/lib/rooms/models.py
lino_voga/lib/sales/__init__.py
lino_voga/lib/sales/models.py
lino_voga/lib/sales/fixtures/__init__.py
lino_voga/lib/sales/fixtures/std.py
lino_voga/lib/voga/__init__.py
