Metadata-Version: 2.1
Name: lino-voga
Version: 23.12.0
Summary: A Lino Django application for managing courses, participants and meeting rooms
Home-page: https://gitlab.com/lino-framework/voga
Author: Rumma & Ko Ltd
Author-email: info@lino-framework.org
Classifier: Programming Language :: Python
Classifier: Programming Language :: Python :: 3
Classifier: Development Status :: 4 - Beta
Classifier: Environment :: Web Environment
Classifier: Framework :: Django
Classifier: Intended Audience :: Developers
Classifier: Intended Audience :: System Administrators
Classifier: Intended Audience :: Education
Classifier: License :: OSI Approved :: GNU Affero General Public License v3
Classifier: Operating System :: OS Independent
Classifier: Topic :: Office/Business :: Financial :: Accounting
Classifier: Topic :: Office/Business :: Scheduling
License-File: COPYING
Requires-Dist: lino_xl
